{
  "schemaVersion": 1,
  "id": "usm",
  "version": "${version}",

  "name": "USM",
  "icon": "assets/usm/icon.png",
  "description": "A new age of steam power",
  "license": "MIT",
  "contact": {
    "sources": "https://github.com/Boundarybreaker/USM"
  },
  "environment": "*",
  "entrypoints": {
    "main": [
      "space.bbkr.usm.USM"
    ],
    "cardinal-components": [
      "space.bbkr.usm.registry.USMComponents"
    ]
  },
  "mixins": [
    "mixins.usm.json"
  ],
  "depends": {
    "fabricloader": ">=0.4.0"
  },
  "custom": {
    "cardinal-components": [
      "usm:steam"
    ]
  }
}
